pynano/nuitka_makeexe.sh.bat
pynano/peach.ico
pynano/pyNanoCMS.exe
pynano/pyinstaller_makeexe.bat
pynano/pynano.py
pynanocms-0.4.3.dist-info/LICENSE
pynanocms-0.4.3.dist-info/METADATA
pynanocms-0.4.3.dist-info/WHEEL
pynanocms-0.4.3.dist-info/entry_points.txt
pynanocms-0.4.3.dist-info/RECORD
