Metadata-Version: 2.1
Name: PyNanoCMS
Version: 0.4.3
Summary: Static site generator
Home-page: https://github.com/rombr/pynano
License: BSD-3-Clause
Keywords: HTTP,static site generator
Author: Roman Bondar
Author-email: rombr5@gmail.com
Requires-Python: >=3.9
Classifier: Development Status :: 5 - Production/Stable
Classifier: Environment :: Web Environment
Classifier: License :: OSI Approved :: BSD License
Classifier: Operating System :: OS Independent
Classifier: Programming Language :: Python :: 3
Classifier: Programming Language :: Python :: 3.9
Classifier: Programming Language :: Python :: 3.10
Classifier: Programming Language :: Python :: 3.11
Classifier: Programming Language :: Python :: 3.12
Classifier: Topic :: Internet :: WWW/HTTP
Requires-Dist: Jinja2
